fastapi_secure_errors/__init__.py
fastapi_secure_errors/exceptions.py
fastapi_secure_errors/handlers.py
fastapi_secure_errors-0.1.2.dist-info/METADATA
fastapi_secure_errors-0.1.2.dist-info/WHEEL
fastapi_secure_errors-0.1.2.dist-info/entry_points.txt
fastapi_secure_errors-0.1.2.dist-info/licenses/LICENSE
fastapi_secure_errors-0.1.2.dist-info/RECORD
