Metadata-Version: 2.4
Name: fastapi-secure-errors
Version: 0.1.2
Summary: Security-first HTTP error handling for FastAPI.
Project-URL: Homepage, https://github.com/ciscomonkey/fastapi-secure-errors
Project-URL: Repository, https://github.com/ciscomonkey/fastapi-secure-errors
Project-URL: Issues, https://github.com/ciscomonkey/fastapi-secure-errors/issues
Project-URL: Changelog, https://github.com/ciscomonkey/fastapi-secure-errors/releases
Author: Ryan Mullins
License-Expression: MIT
License-File: LICENSE
Keywords: api,error-handling,fastapi,http,security
Classifier: Development Status :: 4 - Beta
Classifier: Framework :: FastAPI
Classifier: Intended Audience :: Developers
Classifier: License :: OSI Approved :: MIT License
Classifier: Programming Language :: Python :: 3
Classifier: Programming Language :: Python :: 3.9
Classifier: Programming Language :: Python :: 3.10
Classifier: Programming Language :: Python :: 3.11
Classifier: Programming Language :: Python :: 3.12
Classifier: Programming Language :: Python :: 3.13
Classifier: Topic :: Internet :: WWW/HTTP
Classifier: Topic :: Security
Classifier: Topic :: Software Development :: Libraries :: Python Modules
Requires-Python: >=3.9
Requires-Dist: fastapi>=0.116.1
